[
  {
    "id": "800399d3-dc5d-44e5-b044-436138cf14c0",
    "data": [
      {
        "text": "good afternoon",
        "userDefined": false
      }
    ],
    "isTemplate": false,
    "count": 0,
    "lang": "en",
    "updated": 0
  },
  {
    "id": "b3e5d7fd-f604-46a3-8310-e994467f6b16",
    "data": [
      {
        "text": "good evening",
        "userDefined": false
      }
    ],
    "isTemplate": false,
    "count": 0,
    "lang": "en",
    "updated": 0
  },
  {
    "id": "3eec3f65-cb66-4e13-9efc-35a833e7010e",
    "data": [
      {
        "text": "good morning",
        "userDefined": false
      }
    ],
    "isTemplate": false,
    "count": 0,
    "lang": "en",
    "updated": 0
  },
  {
    "id": "a95de6ae-9b61-4b29-89d1-fe0d61a76b7e",
    "data": [
      {
        "text": "hlo",
        "userDefined": false
      }
    ],
    "isTemplate": false,
    "count": 0,
    "lang": "en",
    "updated": 0
  },
  {
    "id": "510aef64-9f4a-492b-b986-98e49fc1e892",
    "data": [
      {
        "text": "hey there",
        "userDefined": false
      }
    ],
    "isTemplate": false,
    "count": 0,
    "lang": "en",
    "updated": 0
  },
  {
    "id": "64064f44-c8b9-4e88-b034-bb0b33fab272",
    "data": [
      {
        "text": "yo",
        "userDefined": false
      }
    ],
    "isTemplate": false,
    "count": 0,
    "lang": "en",
    "updated": 0
  },
  {
    "id": "b764384d-cefc-42ec-83ba-b1b95f7f8bc9",
    "data": [
      {
        "text": "hey",
        "userDefined": false
      }
    ],
    "isTemplate": false,
    "count": 1,
    "lang": "en",
    "updated": 0
  },
  {
    "id": "21ff1ce2-b446-4b01-8916-40ad7f3be90e",
    "data": [
      {
        "text": "hii",
        "userDefined": false
      }
    ],
    "isTemplate": false,
    "count": 1,
    "lang": "en",
    "updated": 0
  },
  {
    "id": "d37c3acd-1de0-4c65-9d73-cbc75eedbda9",
    "data": [
      {
        "text": "just going to say hi",
        "userDefined": false
      }
    ],
    "isTemplate": false,
    "count": 0,
    "lang": "en",
    "updated": 0
  },
  {
    "id": "668d261d-42b3-4d98-a1c4-bd924f0864d2",
    "data": [
      {
        "text": "heya",
        "userDefined": false
      }
    ],
    "isTemplate": false,
    "count": 0,
    "lang": "en",
    "updated": 0
  },
  {
    "id": "9f06cb10-f124-4b44-9750-82e6d1eace11",
    "data": [
      {
        "text": "hello hi",
        "userDefined": false
      }
    ],
    "isTemplate": false,
    "count": 0,
    "lang": "en",
    "updated": 0
  },
  {
    "id": "8daed3fc-b8ab-40cc-a090-e846b7e93921",
    "data": [
      {
        "text": "howdy",
        "userDefined": false
      }
    ],
    "isTemplate": false,
    "count": 1,
    "lang": "en",
    "updated": 0
  },
  {
    "id": "ba584b3f-500a-41d9-9760-13edb06b34df",
    "data": [
      {
        "text": "hi there",
        "userDefined": false
      }
    ],
    "isTemplate": false,
    "count": 1,
    "lang": "en",
    "updated": 0
  },
  {
    "id": "96c66c75-7701-4bc2-9881-0fd06c0f36cb",
    "data": [
      {
        "text": "greetings",
        "userDefined": false
      }
    ],
    "isTemplate": false,
    "count": 1,
    "lang": "en",
    "updated": 0
  },
  {
    "id": "db081da5-f669-4b4e-b5b4-6aeaed6a812d",
    "data": [
      {
        "text": "long time no see",
        "userDefined": false
      }
    ],
    "isTemplate": false,
    "count": 0,
    "lang": "en",
    "updated": 0
  },
  {
    "id": "5e9cd444-b36a-4b0e-b0a8-d804b4f10dbb",
    "data": [
      {
        "text": "hello",
        "userDefined": false
      }
    ],
    "isTemplate": false,
    "count": 0,
    "lang": "en",
    "updated": 0
  },
  {
    "id": "db856301-3e24-41e8-8ae2-9695f204e912",
    "data": [
      {
        "text": "lovely day isn\u0027t it",
        "userDefined": false
      }
    ],
    "isTemplate": false,
    "count": 0,
    "lang": "en",
    "updated": 0
  },
  {
    "id": "7d0f3b64-8173-423a-89a9-9ca92fb6e117",
    "data": [
      {
        "text": "I greet you",
        "userDefined": false
      }
    ],
    "isTemplate": false,
    "count": 0,
    "lang": "en",
    "updated": 0
  },
  {
    "id": "8bdbdf77-0c20-4a4f-a460-6879fdcf9e70",
    "data": [
      {
        "text": "hello again",
        "userDefined": false
      }
    ],
    "isTemplate": false,
    "count": 0,
    "lang": "en",
    "updated": 0
  },
  {
    "id": "3a4b63d7-cfea-40c4-bf2c-9f0bfaab68d3",
    "data": [
      {
        "text": "hi",
        "userDefined": false
      }
    ],
    "isTemplate": false,
    "count": 0,
    "lang": "en",
    "updated": 0
  },
  {
    "id": "73c1f81e-f9ef-47c6-a6cf-4fe7faa2704f",
    "data": [
      {
        "text": "hello there",
        "userDefined": false
      }
    ],
    "isTemplate": false,
    "count": 0,
    "lang": "en",
    "updated": 0
  },
  {
    "id": "4e80bbb7-f84c-4fb0-acb5-d58ca8f821ca",
    "data": [
      {
        "text": "a good day",
        "userDefined": false
      }
    ],
    "isTemplate": false,
    "count": 0,
    "lang": "en",
    "updated": 0
  }
]